conda_merge.py
conda_merge-0.1.5.dist-info/LICENSE
conda_merge-0.1.5.dist-info/METADATA
conda_merge-0.1.5.dist-info/WHEEL
conda_merge-0.1.5.dist-info/entry_points.txt
conda_merge-0.1.5.dist-info/top_level.txt
conda_merge-0.1.5.dist-info/RECORD
