Metadata-Version: 2.1
Name: conda-merge
Version: 0.1.5
Summary: Tool for merging conda environment files
Home-page: https://github.com/amitbeka/conda-merge
Author: Amit Beka
Author-email: amit.beka@gmail.com
License: MIT
Keywords: conda anaconda environment
Platform: UNKNOWN
Classifier: Development Status :: 4 - Beta
Classifier: Environment :: Console
Classifier: Intended Audience :: Developers
Classifier: License :: OSI Approved :: MIT License
Classifier: Programming Language :: Python :: 3 :: Only
Classifier: Topic :: Software Development :: Build Tools
Classifier: Topic :: System :: Installation/Setup
Requires-Python: >=3
Requires-Dist: pyyaml
Provides-Extra: test
Requires-Dist: pytest ; extra == 'test'
